court_scraper/__init__.py
court_scraper/case_info.py
court_scraper/cli.py
court_scraper/configs.py
court_scraper/datastore.py
court_scraper/db.py
court_scraper/site.py
court_scraper/sites_meta.py
court_scraper/utils.py
court_scraper/base/__init__.py
court_scraper/base/runner.py
court_scraper/base/selenium_helpers.py
court_scraper/base/selenium_site.py
court_scraper/captcha/__init__.py
court_scraper/data/sites_meta.csv
court_scraper/platforms/__init__.py
court_scraper/platforms/odyssey/__init__.py
court_scraper/platforms/odyssey/runner.py
court_scraper/platforms/odyssey/site.py
court_scraper/platforms/odyssey/pages/__init__.py
court_scraper/platforms/odyssey/pages/base.py
court_scraper/platforms/odyssey/pages/case_detail.py
court_scraper/platforms/odyssey/pages/login.py
court_scraper/platforms/odyssey/pages/portal.py
court_scraper/platforms/odyssey/pages/search.py
court_scraper/platforms/odyssey/pages/search_results.py
court_scraper/platforms/oscn/__init__.py
court_scraper/platforms/oscn/runner.py
court_scraper/platforms/oscn/search_results_wrapper.py
court_scraper/platforms/oscn/site.py
court_scraper/platforms/oscn/pages/__init__.py
court_scraper/platforms/oscn/pages/base_search.py
court_scraper/platforms/oscn/pages/case_detail.py
court_scraper/platforms/oscn/pages/case_number_lookup.py
court_scraper/platforms/oscn/pages/daily_filings.py
court_scraper/platforms/oscn/pages/daily_filings_results.py
court_scraper/platforms/oscn/pages/search.py
court_scraper/platforms/oscn/pages/search_results.py
court_scraper/platforms/oscn/parsers/__init__.py
court_scraper/platforms/oscn/parsers/case_detail.py
court_scraper/platforms/wicourts/__init__.py
court_scraper/platforms/wicourts/runner.py
court_scraper/platforms/wicourts/search_api.py
court_scraper/platforms/wicourts/site.py
court_scraper/platforms/wicourts/pages/__init__.py
court_scraper/platforms/wicourts/pages/search.py
court_scraper/platforms/wicourts/pages/search_results.py
court_scraper-0.1.1.dist-info/LICENSE
court_scraper-0.1.1.dist-info/METADATA
court_scraper-0.1.1.dist-info/WHEEL
court_scraper-0.1.1.dist-info/entry_points.txt
court_scraper-0.1.1.dist-info/top_level.txt
court_scraper-0.1.1.dist-info/RECORD
