Metadata-Version: 2.1
Name: court-scraper
Version: 0.1.1
Summary: Command-line tool for scraping data from U.S. county courts
Home-page: https://github.com/biglocalnews/court-scraper
Author: Serdar Tumgoren
Author-email: zstumgoren@gmail.com
License: ISC license
Project-URL: Maintainer, https://github.com/biglocalnews
Project-URL: Source, https://github.com/biglocalnews/court-scraper
Project-URL: Tracker, https://github.com/biglocalnews/court-scraper/issues
Platform: UNKNOWN
Classifier: Development Status :: 4 - Beta
Classifier: Environment :: Console
Classifier: Intended Audience :: Developers
Classifier: License :: OSI Approved :: ISC License (ISCL)
Classifier: Natural Language :: English
Classifier: Programming Language :: Python :: 3
Classifier: Programming Language :: Python :: 3.6
Classifier: Programming Language :: Python :: 3.7
Classifier: Programming Language :: Python :: 3.8
Classifier: Programming Language :: Python :: 3.9
Requires-Dist: anticaptchaofficial
Requires-Dist: bs4
Requires-Dist: click
Requires-Dist: click-option-group
Requires-Dist: lxml
Requires-Dist: my-fake-useragent
Requires-Dist: pyyaml
Requires-Dist: retrying
Requires-Dist: selenium
Requires-Dist: sqlalchemy
Requires-Dist: typing-extensions
